crushlib/__init__.py
crushlib/utils.py
crushlib/crushmap/__init__.py
crushlib/crushmap/buckets.py
crushlib/crushmap/crushmap.py
crushlib/crushmap/devices.py
crushlib/crushmap/parser.py
crushlib/crushmap/rules.py
crushlib/crushmap/tunables.py
crushlib/crushmap/types.py
crushlib-0.2.1.dist-info/LICENSE.txt
crushlib-0.2.1.dist-info/METADATA
crushlib-0.2.1.dist-info/RECORD
crushlib-0.2.1.dist-info/WHEEL
crushlib-0.2.1.dist-info/top_level.txt
